candy_bar/__init__.py
candy_bar/core.cpp
candy_bar/core.cpython-310-aarch64-linux-gnu.so
candy_bar/core.pyx
candy_bar/defs.pxd
candy_bar-2.0.3.dist-info/METADATA
candy_bar-2.0.3.dist-info/WHEEL
candy_bar-2.0.3.dist-info/top_level.txt
candy_bar-2.0.3.dist-info/RECORD
candy_bar-2.0.3.dist-info/licenses/LICENSE
