Metadata-Version: 2.4
Name: candy-bar
Version: 2.0.3
Summary: A simple progress bar with the ILoveCandy style
Author-email: Dumitru Duca <dumitru_duca@outlook.com>
Maintainer-email: Dumitru Duca <dumitru_duca@outlook.com>
License-Expression: MIT
Project-URL: Repository, https://github.com/MacDumi/CandyBar
Keywords: cython,cpp,wrapper
Classifier: Development Status :: 4 - Beta
Classifier: Intended Audience :: Developers
Classifier: Programming Language :: Python :: 3
Classifier: Programming Language :: Python :: 3.9
Classifier: Programming Language :: Python :: 3.10
Classifier: Programming Language :: Python :: 3.11
Classifier: Programming Language :: Python :: 3.12
Classifier: Programming Language :: Python :: 3.13
Classifier: Programming Language :: Cython
Classifier: Programming Language :: C++
Requires-Python: >=3.9
License-File: LICENSE
Dynamic: license-file
